CHANGES.txt
CONTRIBUTORS.rst
LICENSE.txt
MANIFEST.in
README.rst
TODO.txt
checks.py
healthy.py
requirements.txt
requirements_dev.txt
setup.py
healthy.egg-info/PKG-INFO
healthy.egg-info/SOURCES.txt
healthy.egg-info/dependency_links.txt
healthy.egg-info/entry_points.txt
healthy.egg-info/requires.txt
healthy.egg-info/top_level.txt
tests/__init__.py
tests/test_healthy.py