Metadata-Version: 1.1
Name: healthy
Version: 0.1.2
Summary: healthy checks the health of a Python package from its pypi listing
Home-page: https://github.com/dustinmm80/healthy
Author: Dustin Collins
Author-email: dustinrcollins@gmail.com
License: MIT
Platform: UNKNOWN
Classifier: Intended Audience :: Developers
Classifier: Natural Language :: English
Classifier: License :: OSI Approved :: MIT License
Classifier: Programming Language :: Python
Classifier: Programming Language :: Python :: 2
Classifier: Programming Language :: Python :: 2.7
Classifier: Programming Language :: Python :: 3
Classifier: Programming Language :: Python :: 3.2
Classifier: Programming Language :: Python :: 3.3
